tirma/__init__.py
tirma/__main__.py
tirma/properties.yaml
tirma/tirma.py
tirma/tirma_class.py
tirma/objectinfo/InputObjectInfo.py
tirma/objectinfo/InvalidNumberOfSectorsError.py
tirma/objectinfo/MissionInputObjectInfo.py
tirma/objectinfo/MissionObjectInfo.py
tirma/objectinfo/ObjectInfo.py
tirma/objectinfo/ObjectProcessingError.py
tirma/objectinfo/__init__.py
tirma/objectinfo/preparer/LightcurveBuilder.py
tirma/objectinfo/preparer/MissionInputLightcurveBuilder.py
tirma/objectinfo/preparer/MissionLightcurveBuilder.py
tirma/objectinfo/preparer/__init__.py
tirma/star/EpicStarCatalog.py
tirma/star/HabitabilityCalculator.py
tirma/star/KicStarCatalog.py
tirma/star/StarCatalog.py
tirma/star/TicStarCatalog.py
tirma/star/__init__.py
tirma/star/starinfo.py
tirma/tests/__init__.py
tirma/tests/test_tirma.py
tirma-0.1.4.dist-info/LICENSE
tirma-0.1.4.dist-info/METADATA
tirma-0.1.4.dist-info/WHEEL
tirma-0.1.4.dist-info/top_level.txt
tirma-0.1.4.dist-info/RECORD
