Metadata-Version: 2.1
Name: tirma
Version: 0.1.4
Summary: Transit Inject and Recovery Multi-phase Analysis package
Home-page: https://github.com/martindevora/tirma
Author: M. Dévora-Pajares & F.J. Pozuelos
Author-email: mdevorapajares@protonmail.com
License: UNKNOWN
Platform: UNKNOWN
Classifier: Programming Language :: Python :: 3
Classifier: License :: OSI Approved :: MIT License
Classifier: Operating System :: OS Independent
Requires-Python: >=3.6.9
Requires-Dist: cython (==0.29.21)
Requires-Dist: pandas (==1.1.5)
Requires-Dist: lightkurve (==2.0.2)
Requires-Dist: wotan (==1.9)
Requires-Dist: matplotlib (==3.3.4)
Requires-Dist: corner (==2.1.0)
Requires-Dist: ellc (==1.8.5)
Requires-Dist: seaborn (==0.11.1)
Requires-Dist: sklearn (==0.0)
Requires-Dist: scipy (==1.5.4)
Requires-Dist: tess-point (==0.6.1)
Requires-Dist: astropy (==4.1)
Requires-Dist: mock (==4.0.3)
Requires-Dist: tqdm (==4.56.0)
Requires-Dist: setuptools (>=41.0.0)
Requires-Dist: torch (==1.7.1)
Requires-Dist: beautifulsoup4 (==4.9.3)
Requires-Dist: numba (>=0.53.0rc1)
Requires-Dist: batman-package (==2.4.7)
Requires-Dist: argparse (==1.4.0)
Requires-Dist: configparser (==5.0.1)
Requires-Dist: pyparsing (==2.4.7)
Requires-Dist: transitleastsquares (==1.0.25)
Requires-Dist: numpy (==1.19) ; python_version < "3.7"
Requires-Dist: numpy (==1.20.1) ; python_version >= "3.7"
